mistral_lib/__init__.py
mistral_lib/exceptions.py
mistral_lib/serialization.py
mistral_lib/actions/__init__.py
mistral_lib/actions/base.py
mistral_lib/actions/context.py
mistral_lib/actions/types.py
mistral_lib/actions/providers/__init__.py
mistral_lib/actions/providers/base.py
mistral_lib/actions/providers/composite.py
mistral_lib/actions/providers/python.py
mistral_lib/tests/__init__.py
mistral_lib/tests/base.py
mistral_lib/tests/test_inspect_utils.py
mistral_lib/tests/test_serialization.py
mistral_lib/tests/test_utils.py
mistral_lib/tests/actions/__init__.py
mistral_lib/tests/actions/test_action_providers.py
mistral_lib/tests/actions/test_base.py
mistral_lib/tests/actions/test_context.py
mistral_lib/utils/__init__.py
mistral_lib/utils/inspect_utils.py
mistral_lib/yaql/__init__.py
mistral_lib/yaql/api/__init__.py
mistral_lib-3.5.0.dist-info/AUTHORS
mistral_lib-3.5.0.dist-info/LICENSE
mistral_lib-3.5.0.dist-info/METADATA
mistral_lib-3.5.0.dist-info/WHEEL
mistral_lib-3.5.0.dist-info/pbr.json
mistral_lib-3.5.0.dist-info/top_level.txt
mistral_lib-3.5.0.dist-info/RECORD
