Metadata-Version: 2.1
Name: mistral-lib
Version: 3.5.0
Summary: Mistral shared routings and utilities (Actions API, YAQL functions API, data types etc.)
Author-email: OpenStack <openstack-discuss@lists.openstack.org>
License: Apache-2.0
Project-URL: Homepage, https://docs.openstack.org/mistral/latest/
Project-URL: Repository, https://opendev.org/openstack/mistral-lib
Classifier: Environment :: OpenStack
Classifier: Intended Audience :: Information Technology
Classifier: Intended Audience :: System Administrators
Classifier: License :: OSI Approved :: Apache Software License
Classifier: Operating System :: POSIX :: Linux
Classifier: Programming Language :: Python
Classifier: Programming Language :: Python :: 3
Classifier: Programming Language :: Python :: 3.10
Classifier: Programming Language :: Python :: 3.11
Classifier: Programming Language :: Python :: 3.12
Classifier: Programming Language :: Python :: 3.13
Classifier: Programming Language :: Python :: 3 :: Only
Classifier: Programming Language :: Python :: Implementation :: CPython
Requires-Python: >=3.10
License-File: LICENSE
Requires-Dist: oslo.log>=3.36.0
Requires-Dist: pbr!=2.1.0,>=2.0.0
Requires-Dist: oslo.serialization>=2.21.1
Requires-Dist: yaql>=1.1.3
